opentelemetry/instrumentation/eventiq/__init__.py
opentelemetry/instrumentation/eventiq/middlewares.py
opentelemetry/instrumentation/eventiq/model.py
opentelemetry/instrumentation/eventiq/package.py
opentelemetry/instrumentation/eventiq/py.typed
opentelemetry/instrumentation/eventiq/version.py
opentelemetry_instrumentation_eventiq-0.1.5.dist-info/METADATA
opentelemetry_instrumentation_eventiq-0.1.5.dist-info/WHEEL
opentelemetry_instrumentation_eventiq-0.1.5.dist-info/entry_points.txt
opentelemetry_instrumentation_eventiq-0.1.5.dist-info/licenses/LICENSE
opentelemetry_instrumentation_eventiq-0.1.5.dist-info/RECORD
