Metadata-Version: 2.4
Name: opentelemetry-instrumentation-eventiq
Version: 0.1.5
Summary: Opentelemetry instrumentation for eventiq
Project-URL: Documentation, https://github.com/asynq-io/opentelemetry-instrumentation-eventiq#readme
Project-URL: Issues, https://github.com/asynq-io/opentelemetry-instrumentation-eventiq/issues
Project-URL: Source, https://github.com/asynq-io/opentelemetry-instrumentation-eventiq
License-Expression: Apache-2.0
License-File: LICENSE
Classifier: Development Status :: 5 - Production/Stable
Classifier: Framework :: AsyncIO
Classifier: Intended Audience :: Developers
Classifier: License :: OSI Approved :: Apache Software License
Classifier: Natural Language :: English
Classifier: Operating System :: OS Independent
Classifier: Programming Language :: Python :: 3
Classifier: Programming Language :: Python :: 3.9
Classifier: Programming Language :: Python :: 3.10
Classifier: Programming Language :: Python :: 3.11
Classifier: Programming Language :: Python :: 3.12
Classifier: Topic :: Software Development :: Libraries
Requires-Python: >=3.9
Provides-Extra: instruments
Requires-Dist: eventiq>=1.0.0; extra == 'instruments'
